networkinfotranslator/__init__.py
networkinfotranslator/network_info_translator.py
networkinfotranslator/exports/__init__.py
networkinfotranslator/exports/export_base.py
networkinfotranslator/exports/export_cytoscapejs.py
networkinfotranslator/exports/export_escher.py
networkinfotranslator/exports/export_figure_base.py
networkinfotranslator/exports/export_figure_matplotlib.py
networkinfotranslator/exports/export_figure_skia.py
networkinfotranslator/exports/export_json_base.py
networkinfotranslator/exports/export_network_editor.py
networkinfotranslator/exports/export_sbml.py
networkinfotranslator/imports/__init__.py
networkinfotranslator/imports/import_base.py
networkinfotranslator/imports/import_network_editor.py
networkinfotranslator/imports/import_sbml.py
networkinfotranslator/imports/import_sbml_sbne.py
networkinfotranslator-0.5.12.data/scripts/test1.py
networkinfotranslator-0.5.12.dist-info/LICENSE
networkinfotranslator-0.5.12.dist-info/METADATA
networkinfotranslator-0.5.12.dist-info/WHEEL
networkinfotranslator-0.5.12.dist-info/top_level.txt
networkinfotranslator-0.5.12.dist-info/RECORD
